pythagorean_sieve/__init__.py
pythagorean_sieve/sieve.py
pythagorean_sieve-1.0.0.dist-info/licenses/LICENSE
pythagorean_sieve-1.0.0.dist-info/METADATA
pythagorean_sieve-1.0.0.dist-info/WHEEL
pythagorean_sieve-1.0.0.dist-info/top_level.txt
pythagorean_sieve-1.0.0.dist-info/RECORD
