Metadata-Version: 2.4
Name: pythagorean-sieve
Version: 1.0.0
Summary: Pythagorean sieve on the inradius index r (wheel + segmented implementation).
Author-email: Roberto Amato <amato.roberto.py@gmail.com>
License-Expression: AGPL-3.0-or-later
Project-URL: Homepage, https://github.com/amato-roberto-py/pythagorean-sieve
Project-URL: Repository, https://github.com/amato-roberto-py/pythagorean-sieve
Project-URL: Issues, https://github.com/amato-roberto-py/pythagorean-sieve/issues
Keywords: primes,sieve,number-theory,pythagorean,wheel
Classifier: Programming Language :: Python :: 3
Classifier: Operating System :: OS Independent
Classifier: Topic :: Scientific/Engineering :: Mathematics
Requires-Python: >=3.9
License-File: LICENSE
Dynamic: license-file
